db_mockdata/__init__.py
db_mockdata/main.py
db_mockdata-0.4.5.dist-info/LICENSE
db_mockdata-0.4.5.dist-info/METADATA
db_mockdata-0.4.5.dist-info/WHEEL
db_mockdata-0.4.5.dist-info/top_level.txt
db_mockdata-0.4.5.dist-info/RECORD
