Metadata-Version: 2.1
Name: db_mockdata
Version: 0.4.5
Summary: Simple package for creating mockdata for a live database, according to specified relational schema.
Author-email: Mateusz Molenda <devexperrior@gmail.com>
License: MIT License
Project-URL: Repository, https://github.com/Experrior/db-mockdata.git
Project-URL: Issues, https://github.com/Experrior/db-mockdata/issues
Keywords: mock,database,faker
Requires-Python: >=3.8
License-File: LICENSE
Requires-Dist: argparse>=1.4.0
Requires-Dist: faker>=25.2.0
Requires-Dist: networkx>=3.3
Requires-Dist: psycopg2-binary>=2.9.9
Requires-Dist: requests>=2.31.0
Requires-Dist: sqlalchemy>=2.0.30
Requires-Dist: tqdm>=4.66.4
